<?xml version="1.0" encoding="utf-8"?>
<!--
While generating the run time data caches (.rdc files) for animations we are baking entitial transforms of these bones into a cache
to reduce run-time allocations and memory fragmentations.

usefull console commands
memory.dump_animation_cache_memory
mission_cpp.debug_print_animation_entitial_data_details

-->
<base xmlns:xsi="http://www.w3.org/2001/xmlschema-instance" xmlns:xsd="http://www.w3.org/2001/xmlschema"
	type="prebaked_animation">
    <prebaked_animations>
        <animation id="crouch_stand_crossbow" skeleton_name="human_skeleton">
			<bone
				index="4"
				key_list="1,2" />
			<bone
				index="8"
				key_list="1,2" />
			<bone
				index="20"
				key_list="1,3,6,9,12,15,18,21,24,27,30,33,36,39,42,45,48,51,54,57,60,63,66,69,72,75,78,81,84,87,90,93,96,99,102,105,108,111,114,117,120,123,126,129,132,135,138,141,144,147,150,153,155" />
			<bone
				index="27"
				key_list="1,3,6,9,12,15,18,21,24,27,30,33,36,39,42,45,48,51,54,57,60,63,66,69,72,75,78,81,84,87,90,93,96,99,102,105,108,111,114,117,120,123,126,129,132,135,138,141,144,147,150,153,155" />
		</animation>
        <animation id="female_run_backward_crossbow" skeleton_name="human_skeleton">
			<bone
				index="4"
				key_list="15,16" />
			<bone
				index="8"
				key_list="3,4" />
		</animation>
        <animation id="female_run_forward_crossbow" skeleton_name="human_skeleton">
			<bone
				index="4"
				key_list="15,16" />
			<bone
				index="8"
				key_list="3,4" />
		</animation>
        <animation id="female_run_left_crossbow" skeleton_name="human_skeleton">
			<bone
				index="4"
				key_list="16,17" />
			<bone
				index="8"
				key_list="4,5" />
		</animation>
        <animation id="female_run_left_to_right_crossbow" skeleton_name="human_skeleton">
			<bone
				index="4"
				key_list="6,7" />
			<bone
				index="8"
				key_list="18,19" />
		</animation>
        <animation id="female_run_right_crossbow" skeleton_name="human_skeleton">
			<bone
				index="4"
				key_list="16,17" />
			<bone
				index="8"
				key_list="3,4" />
		</animation>
        <animation id="female_run_right_to_left_crossbow" skeleton_name="human_skeleton">
			<bone
				index="4"
				key_list="18,19" />
			<bone
				index="8"
				key_list="6,7" />
		</animation>
        <animation id="female_stand_crossbow" skeleton_name="human_skeleton">
			<bone
				index="4"
				key_list="1,2" />
			<bone
				index="8"
				key_list="1,2" />
		</animation>
        <animation id="female_walk_backward_crossbow" skeleton_name="human_skeleton">
			<bone
				index="4"
				key_list="18,19" />
			<bone
				index="8"
				key_list="3,4" />
		</animation>
        <animation id="female_walk_forward_crossbow" skeleton_name="human_skeleton">
			<bone
				index="4"
				key_list="24,25" />
			<bone
				index="8"
				key_list="8,9" />
		</animation>
        <animation id="female_walk_left_crossbow_2" skeleton_name="human_skeleton">
			<bone
				index="4"
				key_list="22,23" />
			<bone
				index="8"
				key_list="6,7" />
		</animation>
        <animation id="female_walk_left_to_right_crossbow" skeleton_name="human_skeleton">
			<bone
				index="4"
				key_list="4,5" />
			<bone
				index="8"
				key_list="20,21" />
		</animation>
        <animation id="female_walk_right_crossbow_2" skeleton_name="human_skeleton">
			<bone
				index="4"
				key_list="24,25" />
			<bone
				index="8"
				key_list="4,5" />
		</animation>
        <animation id="female_walk_right_to_left_crossbow" skeleton_name="human_skeleton">
			<bone
				index="4"
				key_list="20,21" />
			<bone
				index="8"
				key_list="4,5" />
		</animation>
        <animation id="horse_rider_stand_1_crossbow" skeleton_name="human_skeleton">
			<bone
				index="20"
				key_list="1,3,6,9,12,15,18,21,24,27,30,33,36,39,42,45,48,51,54,57,60,63,66,69,72,75,78,81,84,87,90,93,96,99,102,105,108,111,114,117,120,123,126,129,132,135,138,141,144,147,150,153,156,159,162,165,168,171,174,177,180,183,186,189,192,195,198,201,204,207,210,213,216,219,222,225,228,231,234,237,240,243,246,249,252,255,258,261,264,267,270,273,276,279,282,285,288,291,294,297,300" />
			<bone
				index="27"
				key_list="1,3,6,9,12,15,18,21,24,27,30,33,36,39,42,45,48,51,54,57,60,63,66,69,72,75,78,81,84,87,90,93,96,99,102,105,108,111,114,117,120,123,126,129,132,135,138,141,144,147,150,153,156,159,162,165,168,171,174,177,180,183,186,189,192,195,198,201,204,207,210,213,216,219,222,225,228,231,234,237,240,243,246,249,252,255,258,261,264,267,270,273,276,279,282,285,288,291,294,297,300" />
		</animation>
        <animation id="horse_rider_stand_2_crossbow" skeleton_name="human_skeleton">
			<bone
				index="20"
				key_list="1,3,6,9,12,15,18,21,24,27,30,33,36,39,42,45,48,51,54,57,60,63,66,69,72,75,78,81,84,87,90,93,96,99,102,105,108,111,114,117,120,123,126,129,132,135,138,141,144,147,150,153,156,159,162,165,168,171,174,177,180,183,186,189,192,195,198,201,204,207,210,213,216,219,222,225,228,231,234,237,240,243,246,249,252,255,258,261,264,267,270,273,276,279,282,285,288,291,294,297,300,303,306,309,312,315,318,321,324,327,330,333,336,339,342,345,348,350" />
			<bone
				index="27"
				key_list="1,3,6,9,12,15,18,21,24,27,30,33,36,39,42,45,48,51,54,57,60,63,66,69,72,75,78,81,84,87,90,93,96,99,102,105,108,111,114,117,120,123,126,129,132,135,138,141,144,147,150,153,156,159,162,165,168,171,174,177,180,183,186,189,192,195,198,201,204,207,210,213,216,219,222,225,228,231,234,237,240,243,246,249,252,255,258,261,264,267,270,273,276,279,282,285,288,291,294,297,300,303,306,309,312,315,318,321,324,327,330,333,336,339,342,345,348,350" />
		</animation>
        <animation id="horse_rider_stand_3_crossbow" skeleton_name="human_skeleton">
			<bone
				index="20"
				key_list="1,3,6,9,12,15,18,21,24,27,30,33,36,39,42,45,48,51,54,57,60,63,66,69,72,75,78,81,84,87,90,93,96,99,102,105,108,111,114,117,120,123,126,129,132,135,138,141,144,147,150,153,156,159,162,165,168,171,174,177,180,183,186,189,192,195,198,201,204,207,210,213,216,219,222,225,228,231,234,237,240,243,246,249,252,255,258,261,264,267,270,273,276,279,282,285,288,291,294,297,300,303,306,309,312,315,318,321,324,327,330,333,336,339,342,345,348,351,354,357,360,363,366,369,372,375,378,381,384,387,390,393,396,399,400" />
			<bone
				index="27"
				key_list="1,3,6,9,12,15,18,21,24,27,30,33,36,39,42,45,48,51,54,57,60,63,66,69,72,75,78,81,84,87,90,93,96,99,102,105,108,111,114,117,120,123,126,129,132,135,138,141,144,147,150,153,156,159,162,165,168,171,174,177,180,183,186,189,192,195,198,201,204,207,210,213,216,219,222,225,228,231,234,237,240,243,246,249,252,255,258,261,264,267,270,273,276,279,282,285,288,291,294,297,300,303,306,309,312,315,318,321,324,327,330,333,336,339,342,345,348,351,354,357,360,363,366,369,372,375,378,381,384,387,390,393,396,399,400" />
		</animation>
        <animation id="horse_rider_stand_4_crossbow" skeleton_name="human_skeleton">
			<bone
				index="20"
				key_list="1,3,6,9,12,15,18,21,24,27,30,33,36,39,42,45,48,51,54,57,60,63,66,69,72,75,78,81,84,87,90,93,96,99,102,105,108,111,114,117,120,123,126,129,132,135,138,141,144,147,150,153,156,159,162,165,168,171,174,177,180,183,186,189,192,195,198,201,204,207,210,213,216,219,222,225,228,231,234,237,240,243,246,249,252,255,258,261,264,267,270,273,276,279,282,285,288,291,294,297,300,303,306,309,312,315,318,321,324,327,330,333,336,339,342,345,348,351,354,357,360,363,366,369,372,375,378,381,384,387,390,393,396,399,402,405,408,411,414,417,420,423,426,429,432,435,438,441,444,447,450,453,456,459,460" />
			<bone
				index="27"
				key_list="1,3,6,9,12,15,18,21,24,27,30,33,36,39,42,45,48,51,54,57,60,63,66,69,72,75,78,81,84,87,90,93,96,99,102,105,108,111,114,117,120,123,126,129,132,135,138,141,144,147,150,153,156,159,162,165,168,171,174,177,180,183,186,189,192,195,198,201,204,207,210,213,216,219,222,225,228,231,234,237,240,243,246,249,252,255,258,261,264,267,270,273,276,279,282,285,288,291,294,297,300,303,306,309,312,315,318,321,324,327,330,333,336,339,342,345,348,351,354,357,360,363,366,369,372,375,378,381,384,387,390,393,396,399,402,405,408,411,414,417,420,423,426,429,432,435,438,441,444,447,450,453,456,459,460" />
		</animation>
        <animation id="ready_continue_crossbow" skeleton_name="human_skeleton">
			<bone
				index="20"
				key_list="1,3,6,9,12,15,18,21,24,27,30,33,36,39,42,45,48,51,54,57,60,63,66,69,72,75,78,81,84,87,90,93,96,99,102,105,108,111,114,117,120,123,126,129,132" />
			<bone
				index="27"
				key_list="1,3,6,9,12,15,18,21,24,27,30,33,36,39,42,45,48,51,54,57,60,63,66,69,72,75,78,81,84,87,90,93,96,99,102,105,108,111,114,117,120,123,126,129,132" />
		</animation>
        <animation id="ready_crossbow" skeleton_name="human_skeleton">
			<bone
				index="20"
				key_list="1,3,6,9,12,15,18,20" />
			<bone
				index="27"
				key_list="1,3,6,9,12,15,18,20" />
		</animation>
        <animation id="release_crossbow" skeleton_name="human_skeleton">
			<bone
				index="9"
				key_list="21,22" />
			<bone
				index="10"
				key_list="21,22" />
			<bone
				index="11"
				key_list="21,22" />
			<bone
				index="13"
				key_list="21,22" />
		</animation>
        <animation id="rider_idle_crossbow_1" skeleton_name="human_skeleton">
			<bone
				index="20"
				key_list="1,3,6,9,12,15,18,21,24,27,30,33,36,39,42,45,48,51,54,57,60,63,66,69,72,75,78,81,84,87,90,93,96,99,102,105,108,111,114,117,120,123,126,129,132,135,138,141,144,147,150,153,156,159,162,165,168,171,174,177,180,183,186,189,192,195,198,201,204,207,210,213,216,219,222,225,228,231,234,237,240,243,246,249,252,255,258,261,264,267,270,273,276,279,282,285,288,291,294,297,300,303,306,309,312,315,318,321,324,327,330,333,336,339,342,345,348,351,354,357,360,363,366,369,372,375,378,381,384,387,390,393,396,399,400" />
			<bone
				index="27"
				key_list="1,3,6,9,12,15,18,21,24,27,30,33,36,39,42,45,48,51,54,57,60,63,66,69,72,75,78,81,84,87,90,93,96,99,102,105,108,111,114,117,120,123,126,129,132,135,138,141,144,147,150,153,156,159,162,165,168,171,174,177,180,183,186,189,192,195,198,201,204,207,210,213,216,219,222,225,228,231,234,237,240,243,246,249,252,255,258,261,264,267,270,273,276,279,282,285,288,291,294,297,300,303,306,309,312,315,318,321,324,327,330,333,336,339,342,345,348,351,354,357,360,363,366,369,372,375,378,381,384,387,390,393,396,399,400" />
		</animation>
		<animation id="rider_idle_crossbow_2" skeleton_name="human_skeleton">
			<bone
				index="20"
				key_list="1,3,6,9,12,15,18,21,24,27,30,33,36,39,42,45,48,51,54,57,60,63,66,69,72,75,78,81,84,87,90,93,96,99,102,105,108,111,114,117,120,123,126,129,132,135,138,141,144,147,150,153,156,159,162,165,168,171,174,177,180,183,186,189,192,195,198,201,204,207,210,213,216,219,222,225,228,231,234,237,240,243,246,249,252,255,258,261,264,267,270,273,276,279,282,285,288,291,294,297,300,303,306,309,312,315,318,321,324,327,330,333,336,339,342,345,348,350" />
			<bone
				index="27"
				key_list="1,3,6,9,12,15,18,21,24,27,30,33,36,39,42,45,48,51,54,57,60,63,66,69,72,75,78,81,84,87,90,93,96,99,102,105,108,111,114,117,120,123,126,129,132,135,138,141,144,147,150,153,156,159,162,165,168,171,174,177,180,183,186,189,192,195,198,201,204,207,210,213,216,219,222,225,228,231,234,237,240,243,246,249,252,255,258,261,264,267,270,273,276,279,282,285,288,291,294,297,300,303,306,309,312,315,318,321,324,327,330,333,336,339,342,345,348,350" />
		</animation>
		<animation id="rider_idle_crossbow_3" skeleton_name="human_skeleton">
			<bone
				index="20"
				key_list="1,3,6,9,12,15,18,21,24,27,30,33,36,39,42,45,48,51,54,57,60,63,66,69,72,75,78,81,84,87,90,93,96,99,102,105,108,111,114,117,120,123,126,129,132,135,138,141,144,147,150,153,156,159,162,165,168,171,174,177,180,183,186,189,192,195,198,201,204,207,210,213,216,219,222,225,228,231,234,237,240,243,246,249,252,255,258,261,264,267,270,273,276,279,282,285,288,291,294,297,300,303,306,309,312,315,318,321,324,327,330,333,336,339,342,345,348,351,354,357,360,363,366,369,372,375,378,381,384,387,390,393,396,399,400" />
			<bone
				index="27"
				key_list="1,3,6,9,12,15,18,21,24,27,30,33,36,39,42,45,48,51,54,57,60,63,66,69,72,75,78,81,84,87,90,93,96,99,102,105,108,111,114,117,120,123,126,129,132,135,138,141,144,147,150,153,156,159,162,165,168,171,174,177,180,183,186,189,192,195,198,201,204,207,210,213,216,219,222,225,228,231,234,237,240,243,246,249,252,255,258,261,264,267,270,273,276,279,282,285,288,291,294,297,300,303,306,309,312,315,318,321,324,327,330,333,336,339,342,345,348,351,354,357,360,363,366,369,372,375,378,381,384,387,390,393,396,399,400" />
		</animation>
		<animation id="rider_idle_crossbow_4" skeleton_name="human_skeleton">
			<bone
				index="20"
				key_list="1,3,6,9,12,15,18,21,24,27,30,33,36,39,42,45,48,51,54,57,60,63,66,69,72,75,78,81,84,87,90,93,96,99,102,105,108,111,114,117,120,123,126,129,132,135,138,141,144,147,150,153,156,159,162,165,168,171,174,177,180,183,186,189,192,195,198,201,204,207,210,213,216,219,222,225,228,231,234,237,240,243,246,249,252,255,258,261,264,267,270,273,276,279,282,285,288,291,294,297,300,303,306,309,312,315,318,321,324,327,330,333,336,339,342,345,348,351,354,357,360,363,366,369,372,375,378,381,384,387,390,393,396,399,400" />
			<bone
				index="27"
				key_list="1,3,6,9,12,15,18,21,24,27,30,33,36,39,42,45,48,51,54,57,60,63,66,69,72,75,78,81,84,87,90,93,96,99,102,105,108,111,114,117,120,123,126,129,132,135,138,141,144,147,150,153,156,159,162,165,168,171,174,177,180,183,186,189,192,195,198,201,204,207,210,213,216,219,222,225,228,231,234,237,240,243,246,249,252,255,258,261,264,267,270,273,276,279,282,285,288,291,294,297,300,303,306,309,312,315,318,321,324,327,330,333,336,339,342,345,348,351,354,357,360,363,366,369,372,375,378,381,384,387,390,393,396,399,400" />
		</animation>
        <animation id="run_backward_crossbow" skeleton_name="human_skeleton">
			<bone
				index="4"
				key_list="16,17" />
			<bone
				index="8"
				key_list="3,4" />
		</animation>
        <animation id="run_forward_crossbow" skeleton_name="human_skeleton">
			<bone
				index="4"
				key_list="16,17" />
			<bone
				index="8"
				key_list="3,4" />
		</animation>
        <animation id="run_left_crossbow" skeleton_name="human_skeleton">
			<bone
				index="4"
				key_list="16,17" />
			<bone
				index="8"
				key_list="4,5" />
		</animation>
        <animation id="run_left_to_right_crossbow" skeleton_name="human_skeleton">
			<bone
				index="4"
				key_list="6,7" />
			<bone
				index="8"
				key_list="18,19" />
		</animation>
        <animation id="run_right_crossbow" skeleton_name="human_skeleton">
			<bone
				index="4"
				key_list="16,17" />
			<bone
				index="8"
				key_list="3,4" />
		</animation>
        <animation id="run_right_to_left_crossbow" skeleton_name="human_skeleton">
			<bone
				index="4"
				key_list="18,19" />
			<bone
				index="8"
				key_list="6,7" />
		</animation>
        <animation id="stand_crossbow" skeleton_name="human_skeleton">
			<bone
				index="4"
				key_list="160,161" />
			<bone
				index="8"
				key_list="160,161" />
		</animation>
        <animation id="turn_crossbow" skeleton_name="human_skeleton">
			<bone
				index="4"
				key_list="25,26" />
			<bone
				index="8"
				key_list="12,13" />
		</animation>
        <animation id="walk_backward_crossbow" skeleton_name="human_skeleton">
			<bone
				index="4"
				key_list="18,19" />
			<bone
				index="8"
				key_list="3,4" />
		</animation>
        <animation id="walk_forward_crossbow" skeleton_name="human_skeleton">
			<bone
				index="4"
				key_list="18,19" />
			<bone
				index="8"
				key_list="3,4" />
		</animation>
        <animation id="walk_left_crossbow" skeleton_name="human_skeleton">
			<bone
				index="4"
				key_list="19,20" />
			<bone
				index="8"
				key_list="4,5" />
		</animation>
        <animation id="walk_left_to_right_crossbow" skeleton_name="human_skeleton">
			<bone
				index="4"
				key_list="4,5" />
			<bone
				index="8"
				key_list="20,21" />
		</animation>
        <animation id="walk_right_crossbow" skeleton_name="human_skeleton">
			<bone
				index="4"
				key_list="18,19" />
			<bone
				index="8"
				key_list="3,4" />
		</animation>
        <animation id="walk_right_to_left_crossbow" skeleton_name="human_skeleton">
			<bone
				index="4"
				key_list="20,21" />
			<bone
				index="8"
				key_list="4,5" />
		</animation>
    </prebaked_animations>
</base>